voitta/__init__.py
voitta/voitta.py
voitta/voitta_canvas.py
voitta/voitta_mcp.py
voitta-0.28.0.dist-info/licenses/LICENSE
voitta-0.28.0.dist-info/METADATA
voitta-0.28.0.dist-info/WHEEL
voitta-0.28.0.dist-info/top_level.txt
voitta-0.28.0.dist-info/RECORD
