Metadata-Version: 2.4
Name: voitta
Version: 0.28.0
Summary: A Python framework for LLM tool calls routing, automation, and orchestration
Home-page: https://github.com/voitta-ai/voitta
Author: Voitta
Author-email: support@voitta.ai
Project-URL: Documentation, https://voitta.com
Project-URL: Examples, https://github.com/voitta-ai/voitta-example
Project-URL: Bug Reports, https://github.com/voitta-ai/voitta/issues
Project-URL: Source Code, https://github.com/voitta-ai/voitta
Project-URL: Website, https://voitta.ai
Project-URL: Changelog, https://github.com/voitta-ai/voitta/blob/master/CHANGELOG.md
Classifier: Programming Language :: Python :: 3
Classifier: Programming Language :: Python :: 3.8
Classifier: Programming Language :: Python :: 3.9
Classifier: Programming Language :: Python :: 3.10
Classifier: Programming Language :: Python :: 3.11
Classifier: License :: OSI Approved :: MIT License
Classifier: Operating System :: OS Independent
Classifier: Development Status :: 4 - Beta
Classifier: Intended Audience :: Developers
Classifier: Topic :: Software Development :: Libraries :: Python Modules
License-File: LICENSE
Requires-Dist: dspy>=2.6.16
Requires-Dist: fastapi>=0.95.0
Requires-Dist: uvicorn>=0.21.1
Requires-Dist: python-dotenv>=1.0.0
Requires-Dist: pydantic>=1.10.7
Requires-Dist: requests
Requires-Dist: pandas
Requires-Dist: setuptools
Requires-Dist: pyyaml
Requires-Dist: jsonpath_ng
Requires-Dist: httpx
Requires-Dist: asgiref
Requires-Dist: uuid
Requires-Dist: pyjwt
Dynamic: author
Dynamic: author-email
Dynamic: classifier
Dynamic: description
Dynamic: description-content-type
Dynamic: home-page
Dynamic: license-file
Dynamic: project-url
Dynamic: requires-dist
Dynamic: summary
